setup.py
Rubik/Game.py
Rubik/__init__.py
Rubik.egg-info/PKG-INFO
Rubik.egg-info/SOURCES.txt
Rubik.egg-info/dependency_links.txt
Rubik.egg-info/top_level.txt
Rubik/Controller/CubeMover.py
Rubik/Controller/RubikCube.py
Rubik/Controller/__init__.py
Rubik/Model/Cube.py
Rubik/Model/Piece.py
Rubik/Model/Side.py
Rubik/Model/__init__.py
Rubik/View/Cube3DView.py
Rubik/View/__init__.py
scripts/Rubik.py