Metadata-Version: 1.0
Name: Rubik
Version: 0.0.1
Summary: A Rucik's Cube game.
Home-page: UNKNOWN
Author: Md. Imrul Hassan
Author-email: mdimrul_hassan@yahoo.com
License: BSD
Keywords: Rubik Cube Game Puzzle
Platform: UNKNOWN
Classifier: Development Status :: 3 - Alpha
Classifier: Topic :: Games/Entertainment :: Puzzle Games
Classifier: Environment :: Console
Classifier: Environment :: MacOS X
Classifier: Environment :: Win32 (MS Windows)
Classifier: Intended Audience :: Developers
Classifier: License :: OSI Approved :: GNU General Public License (GPL)
Classifier: Natural Language :: English
Classifier: Programming Language :: Python
